<?xml version="1.0" encoding="UTF-8"?>
<!DOCTYPE nmaprun>
<?xml-stylesheet href="file:///usr/bin/../share/nmap/nmap.xsl" type="text/xsl"?>
<!-- Nmap 7.80 scan initiated Fri May 15 06:36:04 2026 as: nmap -sV -O -p 21,22,23,25,53,80,110,111,139,143,443,445,587,993,995,1521,3306,3389,5432,5900,6379,8080,8443,8888,27017 -T4 -oX /results/batch_13.xml 172.30.2.6 172.30.2.7 172.30.2.8 172.30.2.9 172.30.2.10 -->
<nmaprun scanner="nmap" args="nmap -sV -O -p 21,22,23,25,53,80,110,111,139,143,443,445,587,993,995,1521,3306,3389,5432,5900,6379,8080,8443,8888,27017 -T4 -oX /results/batch_13.xml 172.30.2.6 172.30.2.7 172.30.2.8 172.30.2.9 172.30.2.10" start="1778826964" startstr="Fri May 15 06:36:04 2026" version="7.80" xmloutputversion="1.04">
<scaninfo type="syn" protocol="tcp" numservices="25" services="21-23,25,53,80,110-111,139,143,443,445,587,993,995,1521,3306,3389,5432,5900,6379,8080,8443,8888,27017"/>
<verbose level="0"/>
<debugging level="0"/>
<host starttime="1778826964" endtime="1778826989"><status state="up" reason="arp-response" reason_ttl="0"/>
<address addr="172.30.2.6" addrtype="ipv4"/>
<address addr="E6:37:D4:91:A1:AF" addrtype="mac"/>
<hostnames>
<hostname name="lab-host-2-6.batches_pentest_lab" type="PTR"/>
</hostnames>
<ports><port protocol="tcp" portid="21"><state state="open" reason="syn-ack" reason_ttl="64"/><service name="ftp" product="ProFTPD" version="1.3.5" ostype="Unix" method="probed" conf="10"><cpe>cpe:/a:proftpd:proftpd:1.3.5</cpe></service></port>
<port protocol="tcp" portid="22"><state state="open" reason="syn-ack" reason_ttl="64"/><service name="ssh" product="OpenSSH" version="8.9p1 Ubuntu 3ubuntu0.15" extrainfo="Ubuntu Linux; protocol 2.0" ostype="Linux" method="probed" conf="10"><cpe>cpe:/a:openbsd:openssh:8.9p1</cpe><cpe>cpe:/o:linux:linux_kernel</cpe></service></port>
<port protocol="tcp" portid="23"><state state="closed" reason="reset" reason_ttl="64"/><service name="telnet" method="table" conf="3"/></port>
<port protocol="tcp" portid="25"><state state="closed" reason="reset" reason_ttl="64"/><service name="smtp" method="table" conf="3"/></port>
<port protocol="tcp" portid="53"><state state="closed" reason="reset" reason_ttl="64"/><service name="domain" method="table" conf="3"/></port>
<port protocol="tcp" portid="80"><state state="closed" reason="reset" reason_ttl="64"/><service name="http" method="table" conf="3"/></port>
<port protocol="tcp" portid="110"><state state="closed" reason="reset" reason_ttl="64"/><service name="pop3" method="table" conf="3"/></port>
<port protocol="tcp" portid="111"><state state="closed" reason="reset" reason_ttl="64"/><service name="rpcbind" method="table" conf="3"/></port>
<port protocol="tcp" portid="139"><state state="open" reason="syn-ack" reason_ttl="64"/><service name="netbios-ssn" product="Samba smbd" version="4.6.2" method="probed" conf="10"><cpe>cpe:/a:samba:samba:4.6.2</cpe></service></port>
<port protocol="tcp" portid="143"><state state="closed" reason="reset" reason_ttl="64"/><service name="imap" method="table" conf="3"/></port>
<port protocol="tcp" portid="443"><state state="closed" reason="reset" reason_ttl="64"/><service name="https" method="table" conf="3"/></port>
<port protocol="tcp" portid="445"><state state="open" reason="syn-ack" reason_ttl="64"/><service name="netbios-ssn" product="Samba smbd" version="4.6.2" method="probed" conf="10"><cpe>cpe:/a:samba:samba:4.6.2</cpe></service></port>
<port protocol="tcp" portid="587"><state state="closed" reason="reset" reason_ttl="64"/><service name="submission" method="table" conf="3"/></port>
<port protocol="tcp" portid="993"><state state="closed" reason="reset" reason_ttl="64"/><service name="imaps" method="table" conf="3"/></port>
<port protocol="tcp" portid="995"><state state="closed" reason="reset" reason_ttl="64"/><service name="pop3s" method="table" conf="3"/></port>
<port protocol="tcp" portid="1521"><state state="closed" reason="reset" reason_ttl="64"/><service name="oracle" method="table" conf="3"/></port>
<port protocol="tcp" portid="3306"><state state="closed" reason="reset" reason_ttl="64"/><service name="mysql" method="table" conf="3"/></port>
<port protocol="tcp" portid="3389"><state state="closed" reason="reset" reason_ttl="64"/><service name="ms-wbt-server" method="table" conf="3"/></port>
<port protocol="tcp" portid="5432"><state state="closed" reason="reset" reason_ttl="64"/><service name="postgresql" method="table" conf="3"/></port>
<port protocol="tcp" portid="5900"><state state="closed" reason="reset" reason_ttl="64"/><service name="vnc" method="table" conf="3"/></port>
<port protocol="tcp" portid="6379"><state state="closed" reason="reset" reason_ttl="64"/><service name="redis" method="table" conf="3"/></port>
<port protocol="tcp" portid="8080"><state state="closed" reason="reset" reason_ttl="64"/><service name="http-proxy" method="table" conf="3"/></port>
<port protocol="tcp" portid="8443"><state state="closed" reason="reset" reason_ttl="64"/><service name="https-alt" method="table" conf="3"/></port>
<port protocol="tcp" portid="8888"><state state="closed" reason="reset" reason_ttl="64"/><service name="sun-answerbook" method="table" conf="3"/></port>
<port protocol="tcp" portid="27017"><state state="closed" reason="reset" reason_ttl="64"/><service name="mongod" method="table" conf="3"/></port>
</ports>
<os><portused state="open" proto="tcp" portid="21"/>
<portused state="closed" proto="tcp" portid="23"/>
<portused state="closed" proto="udp" portid="41408"/>
<osmatch name="Linux 2.6.32" accuracy="96" line="55173">
<osclass type="general purpose" vendor="Linux" osfamily="Linux" osgen="2.6.X" accuracy="96"><cpe>cpe:/o:linux:linux_kernel:2.6.32</cpe></osclass>
</osmatch>
<osmatch name="Linux 3.2 - 4.9" accuracy="96" line="65105">
<osclass type="general purpose" vendor="Linux" osfamily="Linux" osgen="3.X" accuracy="96"><cpe>cpe:/o:linux:linux_kernel:3</cpe></osclass>
<osclass type="general purpose" vendor="Linux" osfamily="Linux" osgen="4.X" accuracy="96"><cpe>cpe:/o:linux:linux_kernel:4</cpe></osclass>
</osmatch>
<osmatch name="Linux 2.6.32 - 3.10" accuracy="96" line="56381">
<osclass type="general purpose" vendor="Linux" osfamily="Linux" osgen="2.6.X" accuracy="96"><cpe>cpe:/o:linux:linux_kernel:2.6</cpe></osclass>
<osclass type="general purpose" vendor="Linux" osfamily="Linux" osgen="3.X" accuracy="96"><cpe>cpe:/o:linux:linux_kernel:3</cpe></osclass>
</osmatch>
<osmatch name="Linux 3.4 - 3.10" accuracy="95" line="65366">
<osclass type="general purpose" vendor="Linux" osfamily="Linux" osgen="3.X" accuracy="95"><cpe>cpe:/o:linux:linux_kernel:3</cpe></osclass>
</osmatch>
<osmatch name="Linux 3.1" accuracy="95" line="62708">
<osclass type="general purpose" vendor="Linux" osfamily="Linux" osgen="3.X" accuracy="95"><cpe>cpe:/o:linux:linux_kernel:3.1</cpe></osclass>
</osmatch>
<osmatch name="Linux 3.2" accuracy="95" line="64455">
<osclass type="general purpose" vendor="Linux" osfamily="Linux" osgen="3.X" accuracy="95"><cpe>cpe:/o:linux:linux_kernel:3.2</cpe></osclass>
</osmatch>
<osmatch name="AXIS 210A or 211 Network Camera (Linux 2.6.17)" accuracy="94" line="61606">
<osclass type="webcam" vendor="Linux" osfamily="Linux" osgen="2.6.X" accuracy="94"><cpe>cpe:/o:linux:linux_kernel:2.6.17</cpe></osclass>
<osclass type="webcam" vendor="AXIS" osfamily="embedded" accuracy="94"><cpe>cpe:/h:axis:210a_network_camera</cpe><cpe>cpe:/h:axis:211_network_camera</cpe></osclass>
</osmatch>
<osmatch name="Synology DiskStation Manager 5.2-5644" accuracy="94" line="101159">
<osclass type="storage-misc" vendor="Synology" osfamily="DiskStation Manager" osgen="5.X" accuracy="94"><cpe>cpe:/a:synology:diskstation_manager:5.2</cpe></osclass>
</osmatch>
<osmatch name="Netgear RAIDiator 4.2.28" accuracy="94" line="88023">
<osclass type="storage-misc" vendor="Netgear" osfamily="RAIDiator" osgen="4.X" accuracy="94"><cpe>cpe:/o:netgear:raidiator:4.2.28</cpe></osclass>
</osmatch>
<osmatch name="Linux 2.6.32 - 2.6.35" accuracy="94" line="56153">
<osclass type="general purpose" vendor="Linux" osfamily="Linux" osgen="2.6.X" accuracy="94"><cpe>cpe:/o:linux:linux_kernel:2.6</cpe></osclass>
</osmatch>
<osfingerprint fingerprint="OS:SCAN(V=7.80%E=4%D=5/15%OT=21%CT=23%CU=41408%PV=Y%DS=1%DC=D%G=Y%M=E637D4%&#xa;OS:TM=6A06BEED%P=x86_64-pc-linux-gnu)SEQ(SP=107%GCD=1%ISR=109%TI=Z%CI=Z%II=&#xa;OS:I%TS=A)OPS(O1=M5B4ST11NW7%O2=M5B4ST11NW7%O3=M5B4NNT11NW7%O4=M5B4ST11NW7%&#xa;OS:O5=M5B4ST11NW7%O6=M5B4ST11)WIN(W1=FE88%W2=FE88%W3=FE88%W4=FE88%W5=FE88%W&#xa;OS:6=FE88)ECN(R=Y%DF=Y%T=40%W=FAF0%O=M5B4NNSNW7%CC=Y%Q=)T1(R=Y%DF=Y%T=40%S=&#xa;OS:O%A=S+%F=AS%RD=0%Q=)T2(R=N)T3(R=N)T4(R=Y%DF=Y%T=40%W=0%S=A%A=Z%F=R%O=%RD&#xa;OS:=0%Q=)T5(R=Y%DF=Y%T=40%W=0%S=Z%A=S+%F=AR%O=%RD=0%Q=)T6(R=Y%DF=Y%T=40%W=0&#xa;OS:%S=A%A=Z%F=R%O=%RD=0%Q=)T7(R=Y%DF=Y%T=40%W=0%S=Z%A=S+%F=AR%O=%RD=0%Q=)U1&#xa;OS:(R=Y%DF=N%T=40%IPL=164%UN=0%RIPL=G%RID=G%RIPCK=G%RUCK=G%RUD=G)IE(R=Y%DFI&#xa;OS:=N%T=40%CD=S)&#xa;"/>
</os>
<uptime seconds="1183117" lastboot="Fri May  1 13:57:52 2026"/>
<distance value="1"/>
<tcpsequence index="263" difficulty="Good luck!" values="35C835EF,680F9F36,775F8C3A,27864472,A4EB9A6E,AB8A99EA"/>
<ipidsequence class="All zeros" values="0,0,0,0,0,0"/>
<tcptssequence class="1000HZ" values="4684E8E8,4684E94D,4684E9B1,4684EA15,4684EA79,4684EADD"/>
<times srtt="101" rttvar="22" to="100000"/>
</host>
<host starttime="1778826964" endtime="1778826989"><status state="up" reason="arp-response" reason_ttl="0"/>
<address addr="172.30.2.7" addrtype="ipv4"/>
<address addr="1A:0F:99:6F:89:12" addrtype="mac"/>
<hostnames>
<hostname name="lab-host-2-7.batches_pentest_lab" type="PTR"/>
</hostnames>
<ports><port protocol="tcp" portid="21"><state state="closed" reason="reset" reason_ttl="64"/><service name="ftp" method="table" conf="3"/></port>
<port protocol="tcp" portid="22"><state state="open" reason="syn-ack" reason_ttl="64"/><service name="ssh" product="OpenSSH" version="8.9p1 Ubuntu 3ubuntu0.15" extrainfo="Ubuntu Linux; protocol 2.0" ostype="Linux" method="probed" conf="10"><cpe>cpe:/a:openbsd:openssh:8.9p1</cpe><cpe>cpe:/o:linux:linux_kernel</cpe></service></port>
<port protocol="tcp" portid="23"><state state="closed" reason="reset" reason_ttl="64"/><service name="telnet" method="table" conf="3"/></port>
<port protocol="tcp" portid="25"><state state="closed" reason="reset" reason_ttl="64"/><service name="smtp" method="table" conf="3"/></port>
<port protocol="tcp" portid="53"><state state="closed" reason="reset" reason_ttl="64"/><service name="domain" method="table" conf="3"/></port>
<port protocol="tcp" portid="80"><state state="open" reason="syn-ack" reason_ttl="64"/><service name="http" product="Apache httpd" version="2.4.49" extrainfo="(Unix) OpenSSL/1.1.1d" method="probed" conf="10"><cpe>cpe:/a:apache:http_server:2.4.49</cpe></service></port>
<port protocol="tcp" portid="110"><state state="closed" reason="reset" reason_ttl="64"/><service name="pop3" method="table" conf="3"/></port>
<port protocol="tcp" portid="111"><state state="closed" reason="reset" reason_ttl="64"/><service name="rpcbind" method="table" conf="3"/></port>
<port protocol="tcp" portid="139"><state state="closed" reason="reset" reason_ttl="64"/><service name="netbios-ssn" method="table" conf="3"/></port>
<port protocol="tcp" portid="143"><state state="closed" reason="reset" reason_ttl="64"/><service name="imap" method="table" conf="3"/></port>
<port protocol="tcp" portid="443"><state state="open" reason="syn-ack" reason_ttl="64"/><service name="http" product="Apache httpd" version="2.4.49" extrainfo="(Unix) OpenSSL/1.1.1d" tunnel="ssl" method="probed" conf="10"><cpe>cpe:/a:apache:http_server:2.4.49</cpe></service></port>
<port protocol="tcp" portid="445"><state state="closed" reason="reset" reason_ttl="64"/><service name="microsoft-ds" method="table" conf="3"/></port>
<port protocol="tcp" portid="587"><state state="closed" reason="reset" reason_ttl="64"/><service name="submission" method="table" conf="3"/></port>
<port protocol="tcp" portid="993"><state state="closed" reason="reset" reason_ttl="64"/><service name="imaps" method="table" conf="3"/></port>
<port protocol="tcp" portid="995"><state state="closed" reason="reset" reason_ttl="64"/><service name="pop3s" method="table" conf="3"/></port>
<port protocol="tcp" portid="1521"><state state="closed" reason="reset" reason_ttl="64"/><service name="oracle" method="table" conf="3"/></port>
<port protocol="tcp" portid="3306"><state state="closed" reason="reset" reason_ttl="64"/><service name="mysql" method="table" conf="3"/></port>
<port protocol="tcp" portid="3389"><state state="closed" reason="reset" reason_ttl="64"/><service name="ms-wbt-server" method="table" conf="3"/></port>
<port protocol="tcp" portid="5432"><state state="closed" reason="reset" reason_ttl="64"/><service name="postgresql" method="table" conf="3"/></port>
<port protocol="tcp" portid="5900"><state state="closed" reason="reset" reason_ttl="64"/><service name="vnc" method="table" conf="3"/></port>
<port protocol="tcp" portid="6379"><state state="closed" reason="reset" reason_ttl="64"/><service name="redis" method="table" conf="3"/></port>
<port protocol="tcp" portid="8080"><state state="closed" reason="reset" reason_ttl="64"/><service name="http-proxy" method="table" conf="3"/></port>
<port protocol="tcp" portid="8443"><state state="closed" reason="reset" reason_ttl="64"/><service name="https-alt" method="table" conf="3"/></port>
<port protocol="tcp" portid="8888"><state state="closed" reason="reset" reason_ttl="64"/><service name="sun-answerbook" method="table" conf="3"/></port>
<port protocol="tcp" portid="27017"><state state="closed" reason="reset" reason_ttl="64"/><service name="mongod" method="table" conf="3"/></port>
</ports>
<os><portused state="open" proto="tcp" portid="22"/>
<portused state="closed" proto="tcp" portid="21"/>
<portused state="closed" proto="udp" portid="34333"/>
<osmatch name="Linux 2.6.32" accuracy="96" line="55173">
<osclass type="general purpose" vendor="Linux" osfamily="Linux" osgen="2.6.X" accuracy="96"><cpe>cpe:/o:linux:linux_kernel:2.6.32</cpe></osclass>
</osmatch>
<osmatch name="Linux 3.2 - 4.9" accuracy="96" line="65105">
<osclass type="general purpose" vendor="Linux" osfamily="Linux" osgen="3.X" accuracy="96"><cpe>cpe:/o:linux:linux_kernel:3</cpe></osclass>
<osclass type="general purpose" vendor="Linux" osfamily="Linux" osgen="4.X" accuracy="96"><cpe>cpe:/o:linux:linux_kernel:4</cpe></osclass>
</osmatch>
<osmatch name="Linux 2.6.32 - 3.10" accuracy="96" line="56381">
<osclass type="general purpose" vendor="Linux" osfamily="Linux" osgen="2.6.X" accuracy="96"><cpe>cpe:/o:linux:linux_kernel:2.6</cpe></osclass>
<osclass type="general purpose" vendor="Linux" osfamily="Linux" osgen="3.X" accuracy="96"><cpe>cpe:/o:linux:linux_kernel:3</cpe></osclass>
</osmatch>
<osmatch name="Linux 3.4 - 3.10" accuracy="95" line="65366">
<osclass type="general purpose" vendor="Linux" osfamily="Linux" osgen="3.X" accuracy="95"><cpe>cpe:/o:linux:linux_kernel:3</cpe></osclass>
</osmatch>
<osmatch name="Linux 3.1" accuracy="95" line="62708">
<osclass type="general purpose" vendor="Linux" osfamily="Linux" osgen="3.X" accuracy="95"><cpe>cpe:/o:linux:linux_kernel:3.1</cpe></osclass>
</osmatch>
<osmatch name="Linux 3.2" accuracy="95" line="64455">
<osclass type="general purpose" vendor="Linux" osfamily="Linux" osgen="3.X" accuracy="95"><cpe>cpe:/o:linux:linux_kernel:3.2</cpe></osclass>
</osmatch>
<osmatch name="AXIS 210A or 211 Network Camera (Linux 2.6.17)" accuracy="94" line="61606">
<osclass type="webcam" vendor="Linux" osfamily="Linux" osgen="2.6.X" accuracy="94"><cpe>cpe:/o:linux:linux_kernel:2.6.17</cpe></osclass>
<osclass type="webcam" vendor="AXIS" osfamily="embedded" accuracy="94"><cpe>cpe:/h:axis:210a_network_camera</cpe><cpe>cpe:/h:axis:211_network_camera</cpe></osclass>
</osmatch>
<osmatch name="Synology DiskStation Manager 5.2-5644" accuracy="94" line="101159">
<osclass type="storage-misc" vendor="Synology" osfamily="DiskStation Manager" osgen="5.X" accuracy="94"><cpe>cpe:/a:synology:diskstation_manager:5.2</cpe></osclass>
</osmatch>
<osmatch name="Netgear RAIDiator 4.2.28" accuracy="94" line="88023">
<osclass type="storage-misc" vendor="Netgear" osfamily="RAIDiator" osgen="4.X" accuracy="94"><cpe>cpe:/o:netgear:raidiator:4.2.28</cpe></osclass>
</osmatch>
<osmatch name="Linux 2.6.32 - 2.6.35" accuracy="94" line="56153">
<osclass type="general purpose" vendor="Linux" osfamily="Linux" osgen="2.6.X" accuracy="94"><cpe>cpe:/o:linux:linux_kernel:2.6</cpe></osclass>
</osmatch>
<osfingerprint fingerprint="OS:SCAN(V=7.80%E=4%D=5/15%OT=22%CT=21%CU=34333%PV=Y%DS=1%DC=D%G=Y%M=1A0F99%&#xa;OS:TM=6A06BEED%P=x86_64-pc-linux-gnu)SEQ(SP=108%GCD=1%ISR=10C%TI=Z%CI=Z%II=&#xa;OS:I%TS=A)OPS(O1=M5B4ST11NW7%O2=M5B4ST11NW7%O3=M5B4NNT11NW7%O4=M5B4ST11NW7%&#xa;OS:O5=M5B4ST11NW7%O6=M5B4ST11)WIN(W1=FE88%W2=FE88%W3=FE88%W4=FE88%W5=FE88%W&#xa;OS:6=FE88)ECN(R=Y%DF=Y%T=40%W=FAF0%O=M5B4NNSNW7%CC=Y%Q=)T1(R=Y%DF=Y%T=40%S=&#xa;OS:O%A=S+%F=AS%RD=0%Q=)T2(R=N)T3(R=N)T4(R=Y%DF=Y%T=40%W=0%S=A%A=Z%F=R%O=%RD&#xa;OS:=0%Q=)T5(R=Y%DF=Y%T=40%W=0%S=Z%A=S+%F=AR%O=%RD=0%Q=)T6(R=Y%DF=Y%T=40%W=0&#xa;OS:%S=A%A=Z%F=R%O=%RD=0%Q=)T7(R=Y%DF=Y%T=40%W=0%S=Z%A=S+%F=AR%O=%RD=0%Q=)U1&#xa;OS:(R=Y%DF=N%T=40%IPL=164%UN=0%RIPL=G%RID=G%RIPCK=G%RUCK=G%RUD=G)IE(R=Y%DFI&#xa;OS:=N%T=40%CD=S)&#xa;"/>
</os>
<uptime seconds="3521231" lastboot="Sat Apr  4 12:29:18 2026"/>
<distance value="1"/>
<tcpsequence index="264" difficulty="Good luck!" values="F5B0D21C,6AB6E0B0,7767185E,B771596E,D35EA04E,52D61AD9"/>
<ipidsequence class="All zeros" values="0,0,0,0,0,0"/>
<tcptssequence class="1000HZ" values="D1E1B3A6,D1E1B40A,D1E1B46E,D1E1B4D2,D1E1B536,D1E1B59A"/>
<times srtt="38" rttvar="18" to="100000"/>
</host>
<host starttime="1778826964" endtime="1778826989"><status state="up" reason="arp-response" reason_ttl="0"/>
<address addr="172.30.2.8" addrtype="ipv4"/>
<address addr="F2:96:16:99:8D:61" addrtype="mac"/>
<hostnames>
<hostname name="lab-host-2-8.batches_pentest_lab" type="PTR"/>
</hostnames>
<ports><port protocol="tcp" portid="21"><state state="closed" reason="reset" reason_ttl="64"/><service name="ftp" method="table" conf="3"/></port>
<port protocol="tcp" portid="22"><state state="open" reason="syn-ack" reason_ttl="64"/><service name="ssh" product="OpenSSH" version="8.9p1 Ubuntu 3ubuntu0.15" extrainfo="Ubuntu Linux; protocol 2.0" ostype="Linux" method="probed" conf="10"><cpe>cpe:/a:openbsd:openssh:8.9p1</cpe><cpe>cpe:/o:linux:linux_kernel</cpe></service></port>
<port protocol="tcp" portid="23"><state state="closed" reason="reset" reason_ttl="64"/><service name="telnet" method="table" conf="3"/></port>
<port protocol="tcp" portid="25"><state state="closed" reason="reset" reason_ttl="64"/><service name="smtp" method="table" conf="3"/></port>
<port protocol="tcp" portid="53"><state state="closed" reason="reset" reason_ttl="64"/><service name="domain" method="table" conf="3"/></port>
<port protocol="tcp" portid="80"><state state="open" reason="syn-ack" reason_ttl="64"/><service name="http" product="Apache httpd" version="2.4.49" extrainfo="(Unix) OpenSSL/1.1.1d" method="probed" conf="10"><cpe>cpe:/a:apache:http_server:2.4.49</cpe></service></port>
<port protocol="tcp" portid="110"><state state="closed" reason="reset" reason_ttl="64"/><service name="pop3" method="table" conf="3"/></port>
<port protocol="tcp" portid="111"><state state="closed" reason="reset" reason_ttl="64"/><service name="rpcbind" method="table" conf="3"/></port>
<port protocol="tcp" portid="139"><state state="closed" reason="reset" reason_ttl="64"/><service name="netbios-ssn" method="table" conf="3"/></port>
<port protocol="tcp" portid="143"><state state="closed" reason="reset" reason_ttl="64"/><service name="imap" method="table" conf="3"/></port>
<port protocol="tcp" portid="443"><state state="open" reason="syn-ack" reason_ttl="64"/><service name="http" product="Apache httpd" version="2.4.49" extrainfo="(Unix) OpenSSL/1.1.1d" tunnel="ssl" method="probed" conf="10"><cpe>cpe:/a:apache:http_server:2.4.49</cpe></service></port>
<port protocol="tcp" portid="445"><state state="closed" reason="reset" reason_ttl="64"/><service name="microsoft-ds" method="table" conf="3"/></port>
<port protocol="tcp" portid="587"><state state="closed" reason="reset" reason_ttl="64"/><service name="submission" method="table" conf="3"/></port>
<port protocol="tcp" portid="993"><state state="closed" reason="reset" reason_ttl="64"/><service name="imaps" method="table" conf="3"/></port>
<port protocol="tcp" portid="995"><state state="closed" reason="reset" reason_ttl="64"/><service name="pop3s" method="table" conf="3"/></port>
<port protocol="tcp" portid="1521"><state state="closed" reason="reset" reason_ttl="64"/><service name="oracle" method="table" conf="3"/></port>
<port protocol="tcp" portid="3306"><state state="closed" reason="reset" reason_ttl="64"/><service name="mysql" method="table" conf="3"/></port>
<port protocol="tcp" portid="3389"><state state="closed" reason="reset" reason_ttl="64"/><service name="ms-wbt-server" method="table" conf="3"/></port>
<port protocol="tcp" portid="5432"><state state="open" reason="syn-ack" reason_ttl="64"/><service name="postgresql" product="PostgreSQL DB" version="9.6.0 or later" servicefp="SF-Port5432-TCP:V=7.80%I=7%D=5/15%Time=6A06BEDB%P=x86_64-pc-linux-gnu%r(SMBProgNeg,8C,&quot;E\0\0\0\x8bSFATAL\0VFATAL\0C0A000\0Munsupported\x20frontend\x20protocol\x2065363\.19778:\x20server\x20supports\x203\.0\x20to\x203\.0\0Fpostmaster\.c\0L2165\0RProcessStartupPacket\0\0&quot;);" method="probed" conf="10"><cpe>cpe:/a:postgresql:postgresql</cpe></service></port>
<port protocol="tcp" portid="5900"><state state="closed" reason="reset" reason_ttl="64"/><service name="vnc" method="table" conf="3"/></port>
<port protocol="tcp" portid="6379"><state state="closed" reason="reset" reason_ttl="64"/><service name="redis" method="table" conf="3"/></port>
<port protocol="tcp" portid="8080"><state state="closed" reason="reset" reason_ttl="64"/><service name="http-proxy" method="table" conf="3"/></port>
<port protocol="tcp" portid="8443"><state state="closed" reason="reset" reason_ttl="64"/><service name="https-alt" method="table" conf="3"/></port>
<port protocol="tcp" portid="8888"><state state="closed" reason="reset" reason_ttl="64"/><service name="sun-answerbook" method="table" conf="3"/></port>
<port protocol="tcp" portid="27017"><state state="closed" reason="reset" reason_ttl="64"/><service name="mongod" method="table" conf="3"/></port>
</ports>
<os><portused state="open" proto="tcp" portid="22"/>
<portused state="closed" proto="tcp" portid="21"/>
<portused state="closed" proto="udp" portid="42683"/>
<osmatch name="Linux 2.6.32" accuracy="96" line="55173">
<osclass type="general purpose" vendor="Linux" osfamily="Linux" osgen="2.6.X" accuracy="96"><cpe>cpe:/o:linux:linux_kernel:2.6.32</cpe></osclass>
</osmatch>
<osmatch name="Linux 3.2 - 4.9" accuracy="96" line="65105">
<osclass type="general purpose" vendor="Linux" osfamily="Linux" osgen="3.X" accuracy="96"><cpe>cpe:/o:linux:linux_kernel:3</cpe></osclass>
<osclass type="general purpose" vendor="Linux" osfamily="Linux" osgen="4.X" accuracy="96"><cpe>cpe:/o:linux:linux_kernel:4</cpe></osclass>
</osmatch>
<osmatch name="Linux 2.6.32 - 3.10" accuracy="96" line="56381">
<osclass type="general purpose" vendor="Linux" osfamily="Linux" osgen="2.6.X" accuracy="96"><cpe>cpe:/o:linux:linux_kernel:2.6</cpe></osclass>
<osclass type="general purpose" vendor="Linux" osfamily="Linux" osgen="3.X" accuracy="96"><cpe>cpe:/o:linux:linux_kernel:3</cpe></osclass>
</osmatch>
<osmatch name="Linux 3.4 - 3.10" accuracy="95" line="65366">
<osclass type="general purpose" vendor="Linux" osfamily="Linux" osgen="3.X" accuracy="95"><cpe>cpe:/o:linux:linux_kernel:3</cpe></osclass>
</osmatch>
<osmatch name="Linux 3.1" accuracy="95" line="62708">
<osclass type="general purpose" vendor="Linux" osfamily="Linux" osgen="3.X" accuracy="95"><cpe>cpe:/o:linux:linux_kernel:3.1</cpe></osclass>
</osmatch>
<osmatch name="Linux 3.2" accuracy="95" line="64455">
<osclass type="general purpose" vendor="Linux" osfamily="Linux" osgen="3.X" accuracy="95"><cpe>cpe:/o:linux:linux_kernel:3.2</cpe></osclass>
</osmatch>
<osmatch name="AXIS 210A or 211 Network Camera (Linux 2.6.17)" accuracy="94" line="61606">
<osclass type="webcam" vendor="Linux" osfamily="Linux" osgen="2.6.X" accuracy="94"><cpe>cpe:/o:linux:linux_kernel:2.6.17</cpe></osclass>
<osclass type="webcam" vendor="AXIS" osfamily="embedded" accuracy="94"><cpe>cpe:/h:axis:210a_network_camera</cpe><cpe>cpe:/h:axis:211_network_camera</cpe></osclass>
</osmatch>
<osmatch name="Linux 2.6.32 - 2.6.35" accuracy="94" line="56153">
<osclass type="general purpose" vendor="Linux" osfamily="Linux" osgen="2.6.X" accuracy="94"><cpe>cpe:/o:linux:linux_kernel:2.6</cpe></osclass>
</osmatch>
<osmatch name="Linux 2.6.32 - 3.5" accuracy="94" line="56585">
<osclass type="general purpose" vendor="Linux" osfamily="Linux" osgen="2.6.X" accuracy="94"><cpe>cpe:/o:linux:linux_kernel:2.6</cpe></osclass>
<osclass type="general purpose" vendor="Linux" osfamily="Linux" osgen="3.X" accuracy="94"><cpe>cpe:/o:linux:linux_kernel:3</cpe></osclass>
</osmatch>
<osmatch name="Linux 2.6.32 - 3.13" accuracy="93" line="56411">
<osclass type="general purpose" vendor="Linux" osfamily="Linux" osgen="2.6.X" accuracy="93"><cpe>cpe:/o:linux:linux_kernel:2.6</cpe></osclass>
<osclass type="general purpose" vendor="Linux" osfamily="Linux" osgen="3.X" accuracy="93"><cpe>cpe:/o:linux:linux_kernel:3</cpe></osclass>
</osmatch>
<osfingerprint fingerprint="OS:SCAN(V=7.80%E=4%D=5/15%OT=22%CT=21%CU=42683%PV=Y%DS=1%DC=D%G=Y%M=F29616%&#xa;OS:TM=6A06BEED%P=x86_64-pc-linux-gnu)SEQ(SP=104%GCD=1%ISR=10E%TI=Z%CI=Z%II=&#xa;OS:I%TS=A)OPS(O1=M5B4ST11NW7%O2=M5B4ST11NW7%O3=M5B4NNT11NW7%O4=M5B4ST11NW7%&#xa;OS:O5=M5B4ST11NW7%O6=M5B4ST11)WIN(W1=FE88%W2=FE88%W3=FE88%W4=FE88%W5=FE88%W&#xa;OS:6=FE88)ECN(R=Y%DF=Y%T=40%W=FAF0%O=M5B4NNSNW7%CC=Y%Q=)T1(R=Y%DF=Y%T=40%S=&#xa;OS:O%A=S+%F=AS%RD=0%Q=)T2(R=N)T3(R=N)T4(R=Y%DF=Y%T=40%W=0%S=A%A=Z%F=R%O=%RD&#xa;OS:=0%Q=)T5(R=Y%DF=Y%T=40%W=0%S=Z%A=S+%F=AR%O=%RD=0%Q=)T6(R=Y%DF=Y%T=40%W=0&#xa;OS:%S=A%A=Z%F=R%O=%RD=0%Q=)T7(R=Y%DF=Y%T=40%W=0%S=Z%A=S+%F=AR%O=%RD=0%Q=)U1&#xa;OS:(R=Y%DF=N%T=40%IPL=164%UN=0%RIPL=G%RID=G%RIPCK=G%RUCK=G%RUD=G)IE(R=Y%DFI&#xa;OS:=N%T=40%CD=S)&#xa;"/>
</os>
<uptime seconds="2216875" lastboot="Sun Apr 19 14:48:34 2026"/>
<distance value="1"/>
<tcpsequence index="260" difficulty="Good luck!" values="742650D3,E1194EC3,C6B87F59,4F9307DB,AC9E966B,C528A4E"/>
<ipidsequence class="All zeros" values="0,0,0,0,0,0"/>
<tcptssequence class="1000HZ" values="8422CFCC,8422D030,8422D094,8422D0F8,8422D15C,8422D1C1"/>
<times srtt="27" rttvar="6" to="100000"/>
</host>
<host starttime="1778826964" endtime="1778826989"><status state="up" reason="arp-response" reason_ttl="0"/>
<address addr="172.30.2.9" addrtype="ipv4"/>
<address addr="8E:46:E0:88:48:B5" addrtype="mac"/>
<hostnames>
<hostname name="lab-host-2-9.batches_pentest_lab" type="PTR"/>
</hostnames>
<ports><port protocol="tcp" portid="21"><state state="closed" reason="reset" reason_ttl="64"/><service name="ftp" method="table" conf="3"/></port>
<port protocol="tcp" portid="22"><state state="open" reason="syn-ack" reason_ttl="64"/><service name="ssh" product="OpenSSH" version="8.9p1 Ubuntu 3ubuntu0.15" extrainfo="Ubuntu Linux; protocol 2.0" ostype="Linux" method="probed" conf="10"><cpe>cpe:/a:openbsd:openssh:8.9p1</cpe><cpe>cpe:/o:linux:linux_kernel</cpe></service></port>
<port protocol="tcp" portid="23"><state state="closed" reason="reset" reason_ttl="64"/><service name="telnet" method="table" conf="3"/></port>
<port protocol="tcp" portid="25"><state state="closed" reason="reset" reason_ttl="64"/><service name="smtp" method="table" conf="3"/></port>
<port protocol="tcp" portid="53"><state state="closed" reason="reset" reason_ttl="64"/><service name="domain" method="table" conf="3"/></port>
<port protocol="tcp" portid="80"><state state="open" reason="syn-ack" reason_ttl="64"/><service name="http" product="Apache httpd" version="2.4.49" extrainfo="(Unix) OpenSSL/1.1.1d" method="probed" conf="10"><cpe>cpe:/a:apache:http_server:2.4.49</cpe></service></port>
<port protocol="tcp" portid="110"><state state="closed" reason="reset" reason_ttl="64"/><service name="pop3" method="table" conf="3"/></port>
<port protocol="tcp" portid="111"><state state="closed" reason="reset" reason_ttl="64"/><service name="rpcbind" method="table" conf="3"/></port>
<port protocol="tcp" portid="139"><state state="closed" reason="reset" reason_ttl="64"/><service name="netbios-ssn" method="table" conf="3"/></port>
<port protocol="tcp" portid="143"><state state="closed" reason="reset" reason_ttl="64"/><service name="imap" method="table" conf="3"/></port>
<port protocol="tcp" portid="443"><state state="open" reason="syn-ack" reason_ttl="64"/><service name="http" product="Apache httpd" version="2.4.49" extrainfo="(Unix) OpenSSL/1.1.1d" tunnel="ssl" method="probed" conf="10"><cpe>cpe:/a:apache:http_server:2.4.49</cpe></service></port>
<port protocol="tcp" portid="445"><state state="closed" reason="reset" reason_ttl="64"/><service name="microsoft-ds" method="table" conf="3"/></port>
<port protocol="tcp" portid="587"><state state="closed" reason="reset" reason_ttl="64"/><service name="submission" method="table" conf="3"/></port>
<port protocol="tcp" portid="993"><state state="closed" reason="reset" reason_ttl="64"/><service name="imaps" method="table" conf="3"/></port>
<port protocol="tcp" portid="995"><state state="closed" reason="reset" reason_ttl="64"/><service name="pop3s" method="table" conf="3"/></port>
<port protocol="tcp" portid="1521"><state state="closed" reason="reset" reason_ttl="64"/><service name="oracle" method="table" conf="3"/></port>
<port protocol="tcp" portid="3306"><state state="closed" reason="reset" reason_ttl="64"/><service name="mysql" method="table" conf="3"/></port>
<port protocol="tcp" portid="3389"><state state="closed" reason="reset" reason_ttl="64"/><service name="ms-wbt-server" method="table" conf="3"/></port>
<port protocol="tcp" portid="5432"><state state="closed" reason="reset" reason_ttl="64"/><service name="postgresql" method="table" conf="3"/></port>
<port protocol="tcp" portid="5900"><state state="closed" reason="reset" reason_ttl="64"/><service name="vnc" method="table" conf="3"/></port>
<port protocol="tcp" portid="6379"><state state="closed" reason="reset" reason_ttl="64"/><service name="redis" method="table" conf="3"/></port>
<port protocol="tcp" portid="8080"><state state="closed" reason="reset" reason_ttl="64"/><service name="http-proxy" method="table" conf="3"/></port>
<port protocol="tcp" portid="8443"><state state="closed" reason="reset" reason_ttl="64"/><service name="https-alt" method="table" conf="3"/></port>
<port protocol="tcp" portid="8888"><state state="closed" reason="reset" reason_ttl="64"/><service name="sun-answerbook" method="table" conf="3"/></port>
<port protocol="tcp" portid="27017"><state state="closed" reason="reset" reason_ttl="64"/><service name="mongod" method="table" conf="3"/></port>
</ports>
<os><portused state="open" proto="tcp" portid="22"/>
<portused state="closed" proto="tcp" portid="21"/>
<portused state="closed" proto="udp" portid="35261"/>
<osmatch name="Linux 2.6.32" accuracy="96" line="55173">
<osclass type="general purpose" vendor="Linux" osfamily="Linux" osgen="2.6.X" accuracy="96"><cpe>cpe:/o:linux:linux_kernel:2.6.32</cpe></osclass>
</osmatch>
<osmatch name="Linux 3.2 - 4.9" accuracy="96" line="65105">
<osclass type="general purpose" vendor="Linux" osfamily="Linux" osgen="3.X" accuracy="96"><cpe>cpe:/o:linux:linux_kernel:3</cpe></osclass>
<osclass type="general purpose" vendor="Linux" osfamily="Linux" osgen="4.X" accuracy="96"><cpe>cpe:/o:linux:linux_kernel:4</cpe></osclass>
</osmatch>
<osmatch name="Linux 2.6.32 - 3.10" accuracy="96" line="56381">
<osclass type="general purpose" vendor="Linux" osfamily="Linux" osgen="2.6.X" accuracy="96"><cpe>cpe:/o:linux:linux_kernel:2.6</cpe></osclass>
<osclass type="general purpose" vendor="Linux" osfamily="Linux" osgen="3.X" accuracy="96"><cpe>cpe:/o:linux:linux_kernel:3</cpe></osclass>
</osmatch>
<osmatch name="Linux 3.4 - 3.10" accuracy="95" line="65366">
<osclass type="general purpose" vendor="Linux" osfamily="Linux" osgen="3.X" accuracy="95"><cpe>cpe:/o:linux:linux_kernel:3</cpe></osclass>
</osmatch>
<osmatch name="Linux 3.1" accuracy="95" line="62708">
<osclass type="general purpose" vendor="Linux" osfamily="Linux" osgen="3.X" accuracy="95"><cpe>cpe:/o:linux:linux_kernel:3.1</cpe></osclass>
</osmatch>
<osmatch name="Linux 3.2" accuracy="95" line="64455">
<osclass type="general purpose" vendor="Linux" osfamily="Linux" osgen="3.X" accuracy="95"><cpe>cpe:/o:linux:linux_kernel:3.2</cpe></osclass>
</osmatch>
<osmatch name="AXIS 210A or 211 Network Camera (Linux 2.6.17)" accuracy="94" line="61606">
<osclass type="webcam" vendor="Linux" osfamily="Linux" osgen="2.6.X" accuracy="94"><cpe>cpe:/o:linux:linux_kernel:2.6.17</cpe></osclass>
<osclass type="webcam" vendor="AXIS" osfamily="embedded" accuracy="94"><cpe>cpe:/h:axis:210a_network_camera</cpe><cpe>cpe:/h:axis:211_network_camera</cpe></osclass>
</osmatch>
<osmatch name="Synology DiskStation Manager 5.2-5644" accuracy="94" line="101159">
<osclass type="storage-misc" vendor="Synology" osfamily="DiskStation Manager" osgen="5.X" accuracy="94"><cpe>cpe:/a:synology:diskstation_manager:5.2</cpe></osclass>
</osmatch>
<osmatch name="Netgear RAIDiator 4.2.28" accuracy="94" line="88023">
<osclass type="storage-misc" vendor="Netgear" osfamily="RAIDiator" osgen="4.X" accuracy="94"><cpe>cpe:/o:netgear:raidiator:4.2.28</cpe></osclass>
</osmatch>
<osmatch name="Linux 2.6.32 - 2.6.35" accuracy="94" line="56153">
<osclass type="general purpose" vendor="Linux" osfamily="Linux" osgen="2.6.X" accuracy="94"><cpe>cpe:/o:linux:linux_kernel:2.6</cpe></osclass>
</osmatch>
<osfingerprint fingerprint="OS:SCAN(V=7.80%E=4%D=5/15%OT=22%CT=21%CU=35261%PV=Y%DS=1%DC=D%G=Y%M=8E46E0%&#xa;OS:TM=6A06BEED%P=x86_64-pc-linux-gnu)SEQ(SP=101%GCD=1%ISR=10D%TI=Z%CI=Z%II=&#xa;OS:I%TS=A)OPS(O1=M5B4ST11NW7%O2=M5B4ST11NW7%O3=M5B4NNT11NW7%O4=M5B4ST11NW7%&#xa;OS:O5=M5B4ST11NW7%O6=M5B4ST11)WIN(W1=FE88%W2=FE88%W3=FE88%W4=FE88%W5=FE88%W&#xa;OS:6=FE88)ECN(R=Y%DF=Y%T=40%W=FAF0%O=M5B4NNSNW7%CC=Y%Q=)T1(R=Y%DF=Y%T=40%S=&#xa;OS:O%A=S+%F=AS%RD=0%Q=)T2(R=N)T3(R=N)T4(R=Y%DF=Y%T=40%W=0%S=A%A=Z%F=R%O=%RD&#xa;OS:=0%Q=)T5(R=Y%DF=Y%T=40%W=0%S=Z%A=S+%F=AR%O=%RD=0%Q=)T6(R=Y%DF=Y%T=40%W=0&#xa;OS:%S=A%A=Z%F=R%O=%RD=0%Q=)T7(R=Y%DF=Y%T=40%W=0%S=Z%A=S+%F=AR%O=%RD=0%Q=)U1&#xa;OS:(R=Y%DF=N%T=40%IPL=164%UN=0%RIPL=G%RID=G%RIPCK=G%RUCK=G%RUD=G)IE(R=Y%DFI&#xa;OS:=N%T=40%CD=S)&#xa;"/>
</os>
<uptime seconds="2239452" lastboot="Sun Apr 19 08:32:17 2026"/>
<distance value="1"/>
<tcpsequence index="257" difficulty="Good luck!" values="44D4EB5F,D683DA45,AC22E379,40CF2AC3,8FA00C54,47E2D0B5"/>
<ipidsequence class="All zeros" values="0,0,0,0,0,0"/>
<tcptssequence class="1000HZ" values="857B4DF6,857B4E5A,857B4EBE,857B4F22,857B4F86,857B4FEB"/>
<times srtt="49" rttvar="30" to="100000"/>
</host>
<host starttime="1778826964" endtime="1778826989"><status state="up" reason="arp-response" reason_ttl="0"/>
<address addr="172.30.2.10" addrtype="ipv4"/>
<address addr="76:F3:1A:82:F2:45" addrtype="mac"/>
<hostnames>
<hostname name="lab-host-2-10.batches_pentest_lab" type="PTR"/>
</hostnames>
<ports><port protocol="tcp" portid="21"><state state="closed" reason="reset" reason_ttl="64"/><service name="ftp" method="table" conf="3"/></port>
<port protocol="tcp" portid="22"><state state="open" reason="syn-ack" reason_ttl="64"/><service name="ssh" product="OpenSSH" version="8.9p1 Ubuntu 3ubuntu0.15" extrainfo="Ubuntu Linux; protocol 2.0" ostype="Linux" method="probed" conf="10"><cpe>cpe:/a:openbsd:openssh:8.9p1</cpe><cpe>cpe:/o:linux:linux_kernel</cpe></service></port>
<port protocol="tcp" portid="23"><state state="closed" reason="reset" reason_ttl="64"/><service name="telnet" method="table" conf="3"/></port>
<port protocol="tcp" portid="25"><state state="closed" reason="reset" reason_ttl="64"/><service name="smtp" method="table" conf="3"/></port>
<port protocol="tcp" portid="53"><state state="closed" reason="reset" reason_ttl="64"/><service name="domain" method="table" conf="3"/></port>
<port protocol="tcp" portid="80"><state state="open" reason="syn-ack" reason_ttl="64"/><service name="http" product="Apache httpd" version="2.4.49" extrainfo="(Unix) OpenSSL/1.1.1d" method="probed" conf="10"><cpe>cpe:/a:apache:http_server:2.4.49</cpe></service></port>
<port protocol="tcp" portid="110"><state state="closed" reason="reset" reason_ttl="64"/><service name="pop3" method="table" conf="3"/></port>
<port protocol="tcp" portid="111"><state state="closed" reason="reset" reason_ttl="64"/><service name="rpcbind" method="table" conf="3"/></port>
<port protocol="tcp" portid="139"><state state="closed" reason="reset" reason_ttl="64"/><service name="netbios-ssn" method="table" conf="3"/></port>
<port protocol="tcp" portid="143"><state state="closed" reason="reset" reason_ttl="64"/><service name="imap" method="table" conf="3"/></port>
<port protocol="tcp" portid="443"><state state="open" reason="syn-ack" reason_ttl="64"/><service name="http" product="Apache httpd" version="2.4.49" extrainfo="(Unix) OpenSSL/1.1.1d" tunnel="ssl" method="probed" conf="10"><cpe>cpe:/a:apache:http_server:2.4.49</cpe></service></port>
<port protocol="tcp" portid="445"><state state="closed" reason="reset" reason_ttl="64"/><service name="microsoft-ds" method="table" conf="3"/></port>
<port protocol="tcp" portid="587"><state state="closed" reason="reset" reason_ttl="64"/><service name="submission" method="table" conf="3"/></port>
<port protocol="tcp" portid="993"><state state="closed" reason="reset" reason_ttl="64"/><service name="imaps" method="table" conf="3"/></port>
<port protocol="tcp" portid="995"><state state="closed" reason="reset" reason_ttl="64"/><service name="pop3s" method="table" conf="3"/></port>
<port protocol="tcp" portid="1521"><state state="closed" reason="reset" reason_ttl="64"/><service name="oracle" method="table" conf="3"/></port>
<port protocol="tcp" portid="3306"><state state="closed" reason="reset" reason_ttl="64"/><service name="mysql" method="table" conf="3"/></port>
<port protocol="tcp" portid="3389"><state state="closed" reason="reset" reason_ttl="64"/><service name="ms-wbt-server" method="table" conf="3"/></port>
<port protocol="tcp" portid="5432"><state state="closed" reason="reset" reason_ttl="64"/><service name="postgresql" method="table" conf="3"/></port>
<port protocol="tcp" portid="5900"><state state="closed" reason="reset" reason_ttl="64"/><service name="vnc" method="table" conf="3"/></port>
<port protocol="tcp" portid="6379"><state state="closed" reason="reset" reason_ttl="64"/><service name="redis" method="table" conf="3"/></port>
<port protocol="tcp" portid="8080"><state state="closed" reason="reset" reason_ttl="64"/><service name="http-proxy" method="table" conf="3"/></port>
<port protocol="tcp" portid="8443"><state state="closed" reason="reset" reason_ttl="64"/><service name="https-alt" method="table" conf="3"/></port>
<port protocol="tcp" portid="8888"><state state="closed" reason="reset" reason_ttl="64"/><service name="sun-answerbook" method="table" conf="3"/></port>
<port protocol="tcp" portid="27017"><state state="closed" reason="reset" reason_ttl="64"/><service name="mongod" method="table" conf="3"/></port>
</ports>
<os><portused state="open" proto="tcp" portid="22"/>
<portused state="closed" proto="tcp" portid="21"/>
<portused state="closed" proto="udp" portid="31597"/>
<osmatch name="Linux 2.6.32" accuracy="96" line="55173">
<osclass type="general purpose" vendor="Linux" osfamily="Linux" osgen="2.6.X" accuracy="96"><cpe>cpe:/o:linux:linux_kernel:2.6.32</cpe></osclass>
</osmatch>
<osmatch name="Linux 3.2 - 4.9" accuracy="96" line="65105">
<osclass type="general purpose" vendor="Linux" osfamily="Linux" osgen="3.X" accuracy="96"><cpe>cpe:/o:linux:linux_kernel:3</cpe></osclass>
<osclass type="general purpose" vendor="Linux" osfamily="Linux" osgen="4.X" accuracy="96"><cpe>cpe:/o:linux:linux_kernel:4</cpe></osclass>
</osmatch>
<osmatch name="Linux 2.6.32 - 3.10" accuracy="96" line="56381">
<osclass type="general purpose" vendor="Linux" osfamily="Linux" osgen="2.6.X" accuracy="96"><cpe>cpe:/o:linux:linux_kernel:2.6</cpe></osclass>
<osclass type="general purpose" vendor="Linux" osfamily="Linux" osgen="3.X" accuracy="96"><cpe>cpe:/o:linux:linux_kernel:3</cpe></osclass>
</osmatch>
<osmatch name="Linux 3.4 - 3.10" accuracy="95" line="65366">
<osclass type="general purpose" vendor="Linux" osfamily="Linux" osgen="3.X" accuracy="95"><cpe>cpe:/o:linux:linux_kernel:3</cpe></osclass>
</osmatch>
<osmatch name="Synology DiskStation Manager 5.2-5644" accuracy="95" line="101159">
<osclass type="storage-misc" vendor="Synology" osfamily="DiskStation Manager" osgen="5.X" accuracy="95"><cpe>cpe:/a:synology:diskstation_manager:5.2</cpe></osclass>
</osmatch>
<osmatch name="Linux 3.1" accuracy="95" line="62708">
<osclass type="general purpose" vendor="Linux" osfamily="Linux" osgen="3.X" accuracy="95"><cpe>cpe:/o:linux:linux_kernel:3.1</cpe></osclass>
</osmatch>
<osmatch name="Linux 3.2" accuracy="95" line="64455">
<osclass type="general purpose" vendor="Linux" osfamily="Linux" osgen="3.X" accuracy="95"><cpe>cpe:/o:linux:linux_kernel:3.2</cpe></osclass>
</osmatch>
<osmatch name="AXIS 210A or 211 Network Camera (Linux 2.6.17)" accuracy="94" line="61606">
<osclass type="webcam" vendor="Linux" osfamily="Linux" osgen="2.6.X" accuracy="94"><cpe>cpe:/o:linux:linux_kernel:2.6.17</cpe></osclass>
<osclass type="webcam" vendor="AXIS" osfamily="embedded" accuracy="94"><cpe>cpe:/h:axis:210a_network_camera</cpe><cpe>cpe:/h:axis:211_network_camera</cpe></osclass>
</osmatch>
<osmatch name="Linux 2.6.32 - 2.6.35" accuracy="94" line="56153">
<osclass type="general purpose" vendor="Linux" osfamily="Linux" osgen="2.6.X" accuracy="94"><cpe>cpe:/o:linux:linux_kernel:2.6</cpe></osclass>
</osmatch>
<osmatch name="Linux 2.6.32 - 3.5" accuracy="94" line="56585">
<osclass type="general purpose" vendor="Linux" osfamily="Linux" osgen="2.6.X" accuracy="94"><cpe>cpe:/o:linux:linux_kernel:2.6</cpe></osclass>
<osclass type="general purpose" vendor="Linux" osfamily="Linux" osgen="3.X" accuracy="94"><cpe>cpe:/o:linux:linux_kernel:3</cpe></osclass>
</osmatch>
<osfingerprint fingerprint="OS:SCAN(V=7.80%E=4%D=5/15%OT=22%CT=21%CU=31597%PV=Y%DS=1%DC=D%G=Y%M=76F31A%&#xa;OS:TM=6A06BEED%P=x86_64-pc-linux-gnu)SEQ(SP=FE%GCD=1%ISR=10C%TI=Z%CI=Z%II=I&#xa;OS:%TS=A)OPS(O1=M5B4ST11NW7%O2=M5B4ST11NW7%O3=M5B4NNT11NW7%O4=M5B4ST11NW7%O&#xa;OS:5=M5B4ST11NW7%O6=M5B4ST11)WIN(W1=FE88%W2=FE88%W3=FE88%W4=FE88%W5=FE88%W6&#xa;OS:=FE88)ECN(R=Y%DF=Y%T=40%W=FAF0%O=M5B4NNSNW7%CC=Y%Q=)T1(R=Y%DF=Y%T=40%S=O&#xa;OS:%A=S+%F=AS%RD=0%Q=)T2(R=N)T3(R=N)T4(R=Y%DF=Y%T=40%W=0%S=A%A=Z%F=R%O=%RD=&#xa;OS:0%Q=)T5(R=Y%DF=Y%T=40%W=0%S=Z%A=S+%F=AR%O=%RD=0%Q=)T6(R=Y%DF=Y%T=40%W=0%&#xa;OS:S=A%A=Z%F=R%O=%RD=0%Q=)T7(R=Y%DF=Y%T=40%W=0%S=Z%A=S+%F=AR%O=%RD=0%Q=)U1(&#xa;OS:R=Y%DF=N%T=40%IPL=164%UN=0%RIPL=G%RID=G%RIPCK=G%RUCK=G%RUD=G)IE(R=Y%DFI=&#xa;OS:N%T=40%CD=S)&#xa;"/>
</os>
<uptime seconds="3780098" lastboot="Wed Apr  1 12:34:51 2026"/>
<distance value="1"/>
<tcpsequence index="254" difficulty="Good luck!" values="4A768695,ED0D4E7E,1AABDF77,50E2D94E,904017C,AC4E6FE4"/>
<ipidsequence class="All zeros" values="0,0,0,0,0,0"/>
<tcptssequence class="1000HZ" values="E14FB182,E14FB1E6,E14FB24A,E14FB2AE,E14FB312,E14FB377"/>
<times srtt="32" rttvar="14" to="100000"/>
</host>
<runstats><finished time="1778826989" timestr="Fri May 15 06:36:29 2026" elapsed="25.03" summary="Nmap done at Fri May 15 06:36:29 2026; 5 IP addresses (5 hosts up) scanned in 25.03 seconds" exit="success"/><hosts up="5" down="0" total="5"/>
</runstats>
</nmaprun>
